CONTRIBUTING.rst
HISTORY.rst
LICENSE
MANIFEST.in
README.rst
setup.cfg
setup.py
directsolver/__init__.py
directsolver/directSolver.py
directsolver.egg-info/PKG-INFO
directsolver.egg-info/SOURCES.txt
directsolver.egg-info/dependency_links.txt
directsolver.egg-info/not-zip-safe
directsolver.egg-info/top_level.txt
docs/Makefile
docs/conf.py
docs/contributing.rst
docs/history.rst
docs/index.rst
docs/installation.rst
docs/make.bat
docs/readme.rst
docs/usage.rst
tests/__init__.py
tests/test_directsolver.py